[
  {
    "q": "पृथ्वी के वायुमंडल की सबसे ऊपरी परत कौन-सी है?\nWhich is the outermost layer of Earth’s atmosphere?",
    "options": [
      "क्षोभमंडल (Troposphere)",
      "समतापमंडल (Stratosphere)",
      "आयनमंडल (Ionosphere)",
      "बहिर्मंडल (Exosphere)"
    ],
    "answer_index": 3
  },
  {
    "q": "मानव द्वारा निर्मित नहरें किस संसाधन का उदाहरण हैं?\nMan-made canals are an example of which type of resource?",
    "options": [
      "प्राकृतिक संसाधन (Natural Resource)",
      "अक्षय संसाधन (Renewable Resource)",
      "मानव संसाधन (Human Resource)",
      "मानव निर्मित संसाधन (Human-made Resource)"
    ],
    "answer_index": 3
  },
  {
    "q": "किसी क्षेत्र के ‘पारिस्थितिक तंत्र’ में क्या शामिल होता है?\nWhat does an ecosystem include?",
    "options": [
      "केवल जीवित जीव (Only living organisms)",
      "केवल जलवायु (Only climate)",
      "जीवित और निर्जीव दोनों घटक (Both living and non-living components)",
      "केवल पेड़-पौधे (Only plants)"
    ],
    "answer_index": 2
  },
  {
    "q": "विश्व की सबसे अधिक जनसंख्या घनत्व वाला देश कौन-सा है?\nWhich country has the highest population density?",
    "options": [
      "भारत (India)",
      "बांग्लादेश (Bangladesh)",
      "चीन (China)",
      "जापान (Japan)"
    ],
    "answer_index": 1
  },
  {
    "q": "सवाना घास के मैदान किस महाद्वीप में पाए जाते हैं?\nSavanna grasslands are found in which continent?",
    "options": [
      "एशिया (Asia)",
      "दक्षिण अमेरिका (South America)",
      "अफ्रीका (Africa)",
      "ऑस्ट्रेलिया (Australia)"
    ],
    "answer_index": 2
  },
  {
    "q": "पृथ्वी पर जीवन के लिए सबसे महत्वपूर्ण गैस कौन-सी है?\nWhich gas is most essential for life on Earth?",
    "options": [
      "नाइट्रोजन (Nitrogen)",
      "ऑक्सीजन (Oxygen)",
      "कार्बन डाइऑक्साइड (Carbon Dioxide)",
      "हीलियम (Helium)"
    ],
    "answer_index": 1
  },
  {
    "q": "किस प्रकार की सिंचाई बिजली की मदद से की जाती है?\nWhich type of irrigation is powered by electricity?",
    "options": [
      "नहर सिंचाई (Canal irrigation)",
      "कुएँ की सिंचाई (Well irrigation)",
      "टपक सिंचाई (Drip irrigation)",
      "पंप सिंचाई (Pump irrigation)"
    ],
    "answer_index": 3
  },
  {
    "q": "पृथ्वी की सबसे लंबी पर्वत श्रृंखला कौन-सी है?\nWhich is the longest mountain range on Earth?",
    "options": [
      "हिमालय (Himalayas)",
      "आल्प्स (Alps)",
      "एंडीज (Andes)",
      "रॉकी (Rockies)"
    ],
    "answer_index": 2
  },
  {
    "q": "‘जलवायु परिवर्तन’ का प्रमुख कारण क्या है?\nWhat is the major cause of climate change?",
    "options": [
      "वनों की कटाई (Deforestation)",
      "सूर्य की किरणें",
      "भूकंप",
      "चंद्रमा की गति"
    ],
    "answer_index": 0
  },
  {
    "q": "वह भूमि जिसे वर्ष में एक से अधिक बार जोता जाता है —\nLand which is cultivated more than once in a year is called —",
    "options": [
      "परती भूमि (Fallow land)",
      "स्थाई कृषि (Permanent agriculture)",
      "दो फसली भूमि (Double cropping land)",
      "शुष्क कृषि (Dry farming)"
    ],
    "answer_index": 2
  }
]
